scholaretl/__init__.py
scholaretl/article.py
scholaretl/article_parser.py
scholaretl/py.typed
scholaretl/utils.py
scholaretl/app/__init__.py
scholaretl/app/config.py
scholaretl/app/dependencies.py
scholaretl/app/main.py
scholaretl/app/routers/__init__.py
scholaretl/app/routers/parsing.py
scholaretl/entrypoints/__init__.py
scholaretl/entrypoints/scholaretl_api.py
scholaretl-0.0.6.dist-info/AUTHORS.txt
scholaretl-0.0.6.dist-info/LICENSE.md
scholaretl-0.0.6.dist-info/METADATA
scholaretl-0.0.6.dist-info/WHEEL
scholaretl-0.0.6.dist-info/entry_points.txt
scholaretl-0.0.6.dist-info/top_level.txt
scholaretl-0.0.6.dist-info/RECORD
