Metadata-Version: 2.1
Name: scholaretl
Version: 0.0.6
Summary: ETL for parsing scientific papers.
Author: Blue Brain Project, EPFL
Requires-Python: >=3.10
License-File: LICENSE.md
License-File: AUTHORS.txt
Requires-Dist: asgi-correlation-id
Requires-Dist: dateparser
Requires-Dist: defusedxml
Requires-Dist: fastapi
Requires-Dist: httpx
Requires-Dist: pydantic >=2
Requires-Dist: pydantic-settings
Requires-Dist: python-multipart
Requires-Dist: pypdf
Requires-Dist: uvicorn
Provides-Extra: dev
Requires-Dist: bandit[toml] ; extra == 'dev'
Requires-Dist: mypy ; extra == 'dev'
Requires-Dist: pytest ; extra == 'dev'
Requires-Dist: pytest-cov ; extra == 'dev'
Requires-Dist: ruff ; extra == 'dev'
Requires-Dist: types-dateparser ; extra == 'dev'
Provides-Extra: doc
Requires-Dist: mkdocs ; extra == 'doc'
Requires-Dist: mkdocs-material ; extra == 'doc'
Requires-Dist: mkdocstrings[python] ; extra == 'doc'
